{
  "AJCC": "アメリカJCC",
  "JBCクラシック": "JBCクラシック",
  "JBCスプリント": "JBCスプリント",
  "JBCレディスクラシック": "JBCレディスクラシック",
  "NHKマイルC": "NHKマイルカップ",
  "NHKマイルカップ": "NHKマイルカップ",
  "ＡＪCC": "アメリカJCC",
  "アイビスSD": "アイビスサマーダッシュ",
  "アメリカJCC": "アメリカJCC",
  "アル共杯": "アルゼンチン共和国杯",
  "アルゼンチン": "アルゼンチン共和国杯",
  "アルゼンチン共和国杯": "アルゼンチン共和国杯",
  "エリザベス女王杯": "エリザベス女王杯",
  "オールカマー": "オールカマー",
  "オークス": "オークス",
  "クイーンC": "クイーンカップ",
  "クイーンS": "クイーンステークス",
  "ジャパンC": "ジャパンカップ",
  "ジャパンカップ": "ジャパンカップ",
  "シルクロードS": "シルクロードステークス",
  "スプリング": "スプリングS",
  "スプリングS": "スプリングS",
  "スプリングＳ": "スプリングS",
  "スプリンターズS": "スプリンターズS",
  "セントウルS": "セントウルS",
  "ダービー卿CT": "ダービー卿CT",
  "ダービー卿チャレンジT": "ダービー卿CT",
  "チャンピオンズC": "チャンピオンズカップ",
  "フィリーズR": "フィリーズレビュー",
  "フェブラリーS": "フェブラリーS",
  "フローラS": "フローラS",
  "マイルCS": "マイルCS",
  "マイルチャンピオンシップ": "マイルCS",
  "マイルＣＳ": "マイルCS",
  "ヴィクトリアM": "ヴィクトリアマイル",
  "函館SS": "函館スプリントS",
  "函館スプリントS": "函館スプリントS",
  "高松宮記念": "高松宮記念",
  "天皇賞(春)": "天皇賞・春",
  "天皇賞(秋)": "天皇賞・秋",
  "天皇賞・春": "天皇賞・春",
  "天皇賞・秋": "天皇賞・秋",
  "京成杯AH": "京成杯AH",
  "京成杯オータムH": "京成杯AH",
  "小倉2歳S": "小倉2歳S",
  "新潟2歳S": "新潟2歳S",
  "朝日杯FS": "朝日杯FS",
  "朝日杯フューチュリティS": "朝日杯FS",
  "札幌2歳S": "札幌2歳S",
  "毎日王冠": "毎日王冠",
  "産経大阪杯": "大阪杯",
  "阪神JF": "阪神ジュベナイルF",
  "阪神ジュベナイルF": "阪神ジュベナイルF",
  "阪急杯": "阪急杯"
}
